omu_chat/__init__.py
omu_chat/chat.py
omu_chat/const.py
omu_chat/permissions.py
omu_chat/plugin.py
omu_chat/version.py
omu_chat/event/__init__.py
omu_chat/event/event.py
omu_chat/event/event_types.py
omu_chat/model/__init__.py
omu_chat/model/author.py
omu_chat/model/channel.py
omu_chat/model/content.py
omu_chat/model/gift.py
omu_chat/model/message.py
omu_chat/model/paid.py
omu_chat/model/provider.py
omu_chat/model/reaction.py
omu_chat/model/role.py
omu_chat/model/room.py
omu_chat/model/vote.py
omu_chat-0.9.50.dist-info/METADATA
omu_chat-0.9.50.dist-info/WHEEL
omu_chat-0.9.50.dist-info/entry_points.txt
omu_chat-0.9.50.dist-info/RECORD
